imagefilters-0.6.0.dist-info/METADATA
imagefilters-0.6.0.dist-info/WHEEL
filters/__init__.py
filters/filters.cpython-39-darwin.so
imagefilters-0.6.0.dist-info/RECORD
